thonnycontrib/thonny_etboard_firmware_v2/__init__.py
thonnycontrib/thonny_etboard_firmware_v2/thonny_v3.py
thonnycontrib/thonny_etboard_firmware_v2/thonny_v4.py
thonnycontrib/thonny_etboard_firmware_v2/etboard/firmware/ReadMe.md
thonnycontrib/thonny_etboard_firmware_v2/etboard/firmware/etboard_firmware_micropython_custom_0608_last.bin
thonnycontrib/thonny_etboard_firmware_v2/etboard/firmware/etboard_firmware_micropython_custom_0831_last.bin
thonny_etboard_micropython_firmware_v2-1.0.15.dist-info/LICENSE
thonny_etboard_micropython_firmware_v2-1.0.15.dist-info/METADATA
thonny_etboard_micropython_firmware_v2-1.0.15.dist-info/WHEEL
thonny_etboard_micropython_firmware_v2-1.0.15.dist-info/top_level.txt
thonny_etboard_micropython_firmware_v2-1.0.15.dist-info/RECORD
